nfe/HntException.py
nfe/__init__.py
nfe/constants.py
nfe/nfe_caixa.py
nfe/integrations/form_jira.py
nfe/integrations/issue_jira.py
nfe/integrations/n8n_domain.py
nfe/model/cfop_models.py
nfe/model/cfops.json
nfe/model/dir_fiscal.json
nfe/model/dir_fiscal_models.py
nfe/model/form_automacao_models.py
nfe/model/form_field_id_helper.py
nfe/model/form_nf_caixa_models.py
nfe/model/n8n_domain_model.py
nfe/model/nf_chave_acesso_model.py
nfe/model/nfe_caixa_models.py
nfe/model/nfe_models.py
nfe/notification/jira_comment.py
hnt_nf_caixa_jira_library-0.0.11.dist-info/METADATA
hnt_nf_caixa_jira_library-0.0.11.dist-info/WHEEL
hnt_nf_caixa_jira_library-0.0.11.dist-info/top_level.txt
hnt_nf_caixa_jira_library-0.0.11.dist-info/RECORD
