Metadata-Version: 2.4
Name: hnt_nf_caixa_jira_library
Version: 0.0.11
Summary: Lib to access nf from Jira
Author: Pepe
Maintainer: Pepe
License: MIT License
Keywords: nota_fiscal
Requires-Dist: requests
Requires-Dist: pydantic>=2.5.2
Dynamic: author
Dynamic: keywords
Dynamic: license
Dynamic: maintainer
Dynamic: requires-dist
Dynamic: summary
